limecore/core/cli/__init__.py
limecore/core/cli/argument_parser.py
limecore_core_cli-0.1.1.dist-info/LICENSE.txt
limecore_core_cli-0.1.1.dist-info/METADATA
limecore_core_cli-0.1.1.dist-info/WHEEL
limecore_core_cli-0.1.1.dist-info/top_level.txt
limecore_core_cli-0.1.1.dist-info/RECORD
