Metadata-Version: 2.1
Name: limecore-core-cli
Version: 0.1.1
Summary: limecore: Core CLI
Home-page: https://github.com/limecore/core-cli
Author: Daniel Bradberry
Author-email: daniel@danielbradberry.com
License: MIT
Platform: UNKNOWN
Classifier: Programming Language :: Python :: 3
Classifier: License :: OSI Approved :: MIT License
Classifier: Operating System :: OS Independent
Requires-Python: >=3.6
